nessus_cli/__about__.py
nessus_cli/__init__.py
nessus_cli/main.py
nessus_cli/scans/actions/check.py
nessus_cli/scans/actions/export.py
nessus_cli/scans/actions/list.py
nessus_cli/scans/actions/pause.py
nessus_cli/scans/actions/resume.py
nessus_cli/scans/actions/search.py
nessus_cli/utils/spinner.py
nessus_cli-0.2.1.dist-info/METADATA
nessus_cli-0.2.1.dist-info/WHEEL
nessus_cli-0.2.1.dist-info/entry_points.txt
nessus_cli-0.2.1.dist-info/licenses/LICENSE
nessus_cli-0.2.1.dist-info/RECORD
