Metadata-Version: 2.1
Name: nessus-cli
Version: 0.2.1
Summary: Pause, resume, list, check the status of, or export a Nessus scan. There is also the option to schedule a pause or resume action. Telegram bot support is also included.
Project-URL: Documentation, https://github.com/minniear/nessus-cli#readme
Project-URL: Issues, https://github.com/minniear/nessus-cli/issues
Project-URL: Source, https://github.com/minniear/nessus-cli
Author-email: Luke Minniear <lukeminniear@gmail.com>
License-Expression: GPL-3.0-or-later
License-File: LICENSE
Keywords: nessus,nessus bot,nessus export,nessus pause,nessus resume,nessus schedule,nessus status,nessus telegram,nessus telegram bot,nessus telegram bot export,nessus telegram bot pause,nessus telegram bot resume,nessus telegram bot schedule,nessus telegram bot schedule pause,nessus telegram bot schedule resume,nessus telegram bot status,nessus-cli
Classifier: Development Status :: 4 - Beta
Classifier: Programming Language :: Python
Classifier: Programming Language :: Python :: 3.7
Classifier: Programming Language :: Python :: 3.8
Classifier: Programming Language :: Python :: 3.9
Classifier: Programming Language :: Python :: 3.10
Classifier: Programming Language :: Python :: 3.11
Classifier: Programming Language :: Python :: Implementation :: CPython
Classifier: Programming Language :: Python :: Implementation :: PyPy
Requires-Python: >=3.7
Requires-Dist: certifi==2023.7.22
Requires-Dist: charset-normalizer==3.2.0
Requires-Dist: idna==3.4
Requires-Dist: python-dotenv==1.0.0
Requires-Dist: requests==2.31.0
Requires-Dist: urllib3==2.0.4
